{"cameraMode":{"drawMode":0,"name":"Shaded","section":"Shading Mode"},"sceneLighting":false,"audioPlay":false,"sceneViewState":{"showFog":true,"showMaterialUpdate":false,"showSkybox":false,"showFlares":true,"showImageEffects":true,"showParticleSystems":true},"in2DMode":false,"pivot":{"x":0.04579194635152817,"y":0.008528906852006913,"z":-5.587935447692871e-9},"rotation":{"x":-0.2603400945663452,"y":-0.4811004102230072,"z":0.15215463936328889,"w":-0.8231759071350098},"size":0.06512986123561859,"orthographic":false}